oracle_object_tracker/__init__.py
oracle_object_tracker/database.py
oracle_object_tracker/main.py
oracle_object_tracker-0.0.12.dist-info/licenses/LICENSE
oracle_object_tracker-0.0.12.dist-info/METADATA
oracle_object_tracker-0.0.12.dist-info/WHEEL
oracle_object_tracker-0.0.12.dist-info/entry_points.txt
oracle_object_tracker-0.0.12.dist-info/top_level.txt
oracle_object_tracker-0.0.12.dist-info/RECORD
