Metadata-Version: 2.4
Name: oracle-object-tracker
Version: 0.0.12
Summary: A Python-based tool for tracking Oracle database object DDL with git
Author-email: Philip Moore <philip@gizmodata.com>, Stephen Weber <sweber@truckcab.com>
License-Expression: Apache-2.0
Project-URL: Homepage, https://github.com/TruckCab/oracle-object-tracker
Keywords: oracle,object,tracker,git,ddl
Classifier: Programming Language :: Python
Classifier: Programming Language :: Python :: 3
Requires-Python: >=3.10
License-File: LICENSE
Requires-Dist: click==8.2.*
Requires-Dist: codetiming==1.4.*
Requires-Dist: munch==4.0.*
Requires-Dist: pandas==2.2.*
Requires-Dist: python-dateutil==2.9.*
Requires-Dist: pytz==2025.*
Requires-Dist: PyYAML==6.0.*
Requires-Dist: SQLAlchemy==2.0.*
Requires-Dist: python-dotenv==1.1.*
Requires-Dist: requests==2.32.*
Requires-Dist: oracledb==3.1.*
Requires-Dist: sqlglot==26.28.*
Requires-Dist: gitpython==3.1.*
Provides-Extra: dev
Requires-Dist: bumpver; extra == "dev"
Requires-Dist: pip-tools; extra == "dev"
Requires-Dist: pytest; extra == "dev"
Dynamic: license-file
